ccacards/__init__.py
ccacards/card.py
ccacards/pack.py
ccacards/pile.py
ccacards-0.1.31.dist-info/LICENSE
ccacards-0.1.31.dist-info/METADATA
ccacards-0.1.31.dist-info/WHEEL
ccacards-0.1.31.dist-info/RECORD
