Metadata-Version: 2.1
Name: ccacards
Version: 0.1.31
Summary: python playing cards base
License: GPL-3.0-or-later
Author: ccdale
Author-email: chris.charles.allison+git@gmail.com
Requires-Python: >=3.12,<4.0
Classifier: License :: OSI Approved :: GNU General Public License v3 or later (GPLv3+)
Classifier: Programming Language :: Python :: 3
Classifier: Programming Language :: Python :: 3.12
Requires-Dist: ccaerrors (>=0.1.2,<0.2.0)
Requires-Dist: ccalogging (>=0.5.3,<0.6.0)
Requires-Dist: pillow (>=11.0.0,<12.0.0)
Requires-Dist: platformdirs (>=4.3.6,<5.0.0)
